setup.py
twsd/__init__.py
twsd/auth.py
twsd/db.py
twsd/tests.py
twsd/twsd.py
twsd/yn.py
twsd.egg-info/PKG-INFO
twsd.egg-info/SOURCES.txt
twsd.egg-info/dependency_links.txt
twsd.egg-info/entry_points.txt
twsd.egg-info/pbr.json
twsd.egg-info/requires.txt
twsd.egg-info/top_level.txt