Metadata-Version: 1.0
Name: twsd
Version: 0.1.1
Summary: Twitter Stream Downloader.
Home-page: UNKNOWN
Author: Antonio Lima
Author-email: anto87@gmail.com
License: UNKNOWN
Platform: UNKNOWN
